here_routing/__init__.py
here_routing/exceptions.py
here_routing/here_routing.py
here_routing/model.py
here_routing-1.1.3.dist-info/METADATA
here_routing-1.1.3.dist-info/WHEEL
here_routing-1.1.3.dist-info/licenses/LICENSE
here_routing-1.1.3.dist-info/RECORD
