Metadata-Version: 2.4
Name: here_routing
Version: 1.1.3
Summary: Asynchronous Python client for the HERE Routing V8 API
Author-email: Kevin Stillhammer <kevin.stillhammer@gmail.com>
License-Expression: MIT
License-File: LICENSE
Keywords: aiohttp,asyncio,here,here-api,routing
Classifier: Intended Audience :: Developers
Classifier: License :: OSI Approved :: MIT License
Classifier: Operating System :: OS Independent
Classifier: Programming Language :: Python
Classifier: Programming Language :: Python :: 3
Classifier: Topic :: Software Development :: Libraries :: Python Modules
Requires-Python: >=3.10
Requires-Dist: aiohttp>=3.12.4
Requires-Dist: async-timeout>=4.0.3
Requires-Dist: yarl>=1.20.0
